dsiter/__init__.py
dsiter/collection.py
dsiter/dataset_item.py
dsiter/utils/common.py
dsiter-0.1.0.dist-info/METADATA
dsiter-0.1.0.dist-info/WHEEL
dsiter-0.1.0.dist-info/licenses/LICENSE
dsiter-0.1.0.dist-info/RECORD
