Metadata-Version: 2.4
Name: dsiter
Version: 0.1.0
Summary: A library for iterating over aggregated datasets from HuggingFace and local CSV files
License-File: LICENSE
Requires-Python: >=3.9
Requires-Dist: datasets>=4.0.0
Requires-Dist: pyyaml>=6.0
